PandasXuexiShouceZhongwenDierBanChuyiFix1/README.md
PandasXuexiShouceZhongwenDierBanChuyiFix1/__init__.py
PandasXuexiShouceZhongwenDierBanChuyiFix1/__main__.py
PandasXuexiShouceZhongwenDierBanChuyiFix1/file.epub
PandasXuexiShouceZhongwenDierBanChuyiFix1/index.html
PandasXuexiShouceZhongwenDierBanChuyiFix1/css/__init__.py
PandasXuexiShouceZhongwenDierBanChuyiFix1/css/annotations.css
PandasXuexiShouceZhongwenDierBanChuyiFix1/css/main.css
PandasXuexiShouceZhongwenDierBanChuyiFix1/css/normalize.css
PandasXuexiShouceZhongwenDierBanChuyiFix1/css/popup.css
PandasXuexiShouceZhongwenDierBanChuyiFix1/font/__init__.py
PandasXuexiShouceZhongwenDierBanChuyiFix1/font/fontello.eot
PandasXuexiShouceZhongwenDierBanChuyiFix1/font/fontello.svg
PandasXuexiShouceZhongwenDierBanChuyiFix1/font/fontello.ttf
PandasXuexiShouceZhongwenDierBanChuyiFix1/font/fontello.woff
PandasXuexiShouceZhongwenDierBanChuyiFix1/img/__init__.py
PandasXuexiShouceZhongwenDierBanChuyiFix1/img/annotator-glyph-sprite.png
PandasXuexiShouceZhongwenDierBanChuyiFix1/img/annotator-icon-sprite.png
PandasXuexiShouceZhongwenDierBanChuyiFix1/img/apple-touch-icon.png
PandasXuexiShouceZhongwenDierBanChuyiFix1/img/cancelfullscreen.png
PandasXuexiShouceZhongwenDierBanChuyiFix1/img/close.png
PandasXuexiShouceZhongwenDierBanChuyiFix1/img/fullscreen.png
PandasXuexiShouceZhongwenDierBanChuyiFix1/img/loader.gif
PandasXuexiShouceZhongwenDierBanChuyiFix1/img/menu-icon.png
PandasXuexiShouceZhongwenDierBanChuyiFix1/img/save.png
PandasXuexiShouceZhongwenDierBanChuyiFix1/img/saved.png
PandasXuexiShouceZhongwenDierBanChuyiFix1/img/settings-s.png
PandasXuexiShouceZhongwenDierBanChuyiFix1/img/settings.png
PandasXuexiShouceZhongwenDierBanChuyiFix1/img/star.png
PandasXuexiShouceZhongwenDierBanChuyiFix1/js/__init__.py
PandasXuexiShouceZhongwenDierBanChuyiFix1/js/epub.js
PandasXuexiShouceZhongwenDierBanChuyiFix1/js/epub.min.js
PandasXuexiShouceZhongwenDierBanChuyiFix1/js/epub.min.map
PandasXuexiShouceZhongwenDierBanChuyiFix1/js/hooks.min.js
pandas_xuexi_shouce_zhongwen_dier_ban_chuyi_fix1-2025.3.24.1.dist-info/METADATA
pandas_xuexi_shouce_zhongwen_dier_ban_chuyi_fix1-2025.3.24.1.dist-info/WHEEL
pandas_xuexi_shouce_zhongwen_dier_ban_chuyi_fix1-2025.3.24.1.dist-info/entry_points.txt
pandas_xuexi_shouce_zhongwen_dier_ban_chuyi_fix1-2025.3.24.1.dist-info/top_level.txt
pandas_xuexi_shouce_zhongwen_dier_ban_chuyi_fix1-2025.3.24.1.dist-info/RECORD
